log2influx/__init__.py
log2influx/log2influx.py
log2influx-0.2.0.dist-info/AUTHORS.rst
log2influx-0.2.0.dist-info/LICENSE
log2influx-0.2.0.dist-info/METADATA
log2influx-0.2.0.dist-info/WHEEL
log2influx-0.2.0.dist-info/entry_points.txt
log2influx-0.2.0.dist-info/top_level.txt
log2influx-0.2.0.dist-info/RECORD
