Metadata-Version: 2.1
Name: log2influx
Version: 0.2.0
Summary: Utility to write logging to influxdb2 in order to gather some application stats. After using this utility, user can create dashboard in Grafana with InfluxDB.
Home-page: https://github.com/robsonyeg/log2influx
Author: Robin Song
Author-email: robin.song@edmonton.ca
License: MIT license
Keywords: log2influx
Classifier: Development Status :: 2 - Pre-Alpha
Classifier: Intended Audience :: Developers
Classifier: License :: OSI Approved :: MIT License
Classifier: Natural Language :: English
Classifier: Programming Language :: Python :: 3
Classifier: Programming Language :: Python :: 3.8
Classifier: Programming Language :: Python :: 3.9
Requires-Python: >=3.8
License-File: LICENSE
License-File: AUTHORS.rst
Requires-Dist: influxdb-client[async] (>=1.29.1)
